README.md
setup.py
dsnd_distributions/Binomialdistribution.py
dsnd_distributions/Gaussiandistribution.py
dsnd_distributions/Generaldistribution.py
dsnd_distributions/__init__.py
dsnd_distributions_060519930469.egg-info/PKG-INFO
dsnd_distributions_060519930469.egg-info/SOURCES.txt
dsnd_distributions_060519930469.egg-info/dependency_links.txt
dsnd_distributions_060519930469.egg-info/not-zip-safe
dsnd_distributions_060519930469.egg-info/top_level.txt