Metadata-Version: 1.0
Name: dsnd-distributions-060519930469
Version: 0.1
Summary: Gaussian distributions
Home-page: UNKNOWN
Author: Giang Le
Author-email: giang.lh0469@gmail.com
License: UNKNOWN
Platform: UNKNOWN
